[
	{
		"verse": "¿Por qué se amotinan las gentes, Y los pueblos piensan cosas vanas?",
		"number": 1
	},
	{
		"verse": "Se levantarán los reyes de la tierra, Y príncipes consultarán unidos Contra Jehová y contra su ungido, diciendo:",
		"number": 2
	},
	{
		"verse": "Rompamos sus ligaduras, Y echemos de nosotros sus cuerdas.",
		"number": 3
	},
	{
		"verse": "El que mora en los cielos se reirá; El Señor se burlará de ellos.",
		"number": 4
	},
	{
		"verse": "Luego hablará a ellos en su furor, Y los turbará con su ira.",
		"number": 5
	},
	{
		"verse": "Pero yo he puesto mi rey Sobre Sion, mi santo monte.",
		"number": 6
	},
	{
		"verse": "Yo publicaré el decreto; Jehová me ha dicho: Mi hijo eres tú; Yo te engendré hoy.",
		"number": 7
	},
	{
		"verse": "Pídeme, y te daré por herencia las naciones, Y como posesión tuya los confines de la tierra.",
		"number": 8
	},
	{
		"verse": "Los quebrantarás con vara de hierro; Como vasija de alfarero los desmenuzarás.",
		"number": 9
	},
	{
		"verse": "Ahora, pues, oh reyes, sed prudentes; Admitid amonestación, jueces de la tierra.",
		"number": 10
	},
	{
		"verse": "Servid a Jehová con temor, Y alegraos con temblor.",
		"number": 11
	},
	{
		"verse": "Honrad al Hijo, para que no se enoje, y perezcáis en el camino; Pues se inflama de pronto su ira. Bienaventurados todos los que en él confían.",
		"number": 12
	}
]