[
	{
		"verse": "Hijo mío, está atento a mi sabiduría, Y a mi inteligencia inclina tu oído,",
		"number": 1
	},
	{
		"verse": "Para que guardes consejo, Y tus labios conserven la ciencia.",
		"number": 2
	},
	{
		"verse": "Porque los labios de la mujer extraña destilan miel, Y su paladar es más blando que el aceite;",
		"number": 3
	},
	{
		"verse": "Mas su fin es amargo como el ajenjo, Agudo como espada de dos filos.",
		"number": 4
	},
	{
		"verse": "Sus pies descienden a la muerte; Sus pasos conducen al Seol.",
		"number": 5
	},
	{
		"verse": "Sus caminos son inestables; no los conocerás, Si no considerares el camino de vida.",
		"number": 6
	},
	{
		"verse": "Ahora pues, hijos, oídme, Y no os apartéis de las razones de mi boca.",
		"number": 7
	},
	{
		"verse": "Aleja de ella tu camino, Y no te acerques a la puerta de su casa;",
		"number": 8
	},
	{
		"verse": "Para que no des a los extraños tu honor, Y tus años al cruel;",
		"number": 9
	},
	{
		"verse": "No sea que extraños se sacien de tu fuerza, Y tus trabajos estén en casa del extraño;",
		"number": 10
	},
	{
		"verse": "Y gimas al final, Cuando se consuma tu carne y tu cuerpo,",
		"number": 11
	},
	{
		"verse": "Y digas: ¡Cómo aborrecí el consejo, Y mi corazón menospreció la reprensión;",
		"number": 12
	},
	{
		"verse": "No oí la voz de los que me instruían, Y a los que me enseñaban no incliné mi oído!",
		"number": 13
	},
	{
		"verse": "Casi en todo mal he estado, En medio de la sociedad y de la congregación.",
		"number": 14
	},
	{
		"verse": "Bebe el agua de tu misma cisterna, Y los raudales de tu propio pozo.",
		"number": 15
	},
	{
		"verse": "¿Se derramarán tus fuentes por las calles, Y tus corrientes de aguas por las plazas?",
		"number": 16
	},
	{
		"verse": "Sean para ti solo, Y no para los extraños contigo.",
		"number": 17
	},
	{
		"verse": "Sea bendito tu manantial, Y alégrate con la mujer de tu juventud,",
		"number": 18
	},
	{
		"verse": "Como cierva amada y graciosa gacela. Sus caricias te satisfagan en todo tiempo, Y en su amor recréate siempre.",
		"number": 19
	},
	{
		"verse": "¿Y por qué, hijo mío, andarás ciego con la mujer ajena, Y abrazarás el seno de la extraña?",
		"number": 20
	},
	{
		"verse": "Porque los caminos del hombre están ante los ojos de Jehová, Y él considera todas sus veredas.",
		"number": 21
	},
	{
		"verse": "Prenderán al impío sus propias iniquidades, Y retenido será con las cuerdas de su pecado.",
		"number": 22
	},
	{
		"verse": "El morirá por falta de corrección, Y errará por lo inmenso de su locura.",
		"number": 23
	}
]